lexorank/__init__.py
lexorank/lexorank.py
lexorank-1.0.1.dist-info/WHEEL
lexorank-1.0.1.dist-info/METADATA
lexorank-1.0.1.dist-info/RECORD
